flask_foreignkey.py
flask_foreignkey-0.2.dist-info/COPYING.txt
flask_foreignkey-0.2.dist-info/METADATA
flask_foreignkey-0.2.dist-info/WHEEL
flask_foreignkey-0.2.dist-info/top_level.txt
flask_foreignkey-0.2.dist-info/RECORD
