Metadata-Version: 2.1
Name: flask-foreignkey
Version: 0.2
Summary: Use class decorator to add foreign keys.
Home-page: https://github.com/ShakeM/flask-foreignkey
Author: Jonathan Nuance
Author-email: jonathan.nuance@outlook.com
License: MIT
Platform: any
Classifier: Environment :: Web Environment
Classifier: Intended Audience :: Developers
Classifier: License :: OSI Approved :: BSD License
Classifier: Operating System :: OS Independent
Classifier: Programming Language :: Python
Classifier: Topic :: Internet :: WWW/HTTP :: Dynamic Content
Classifier: Topic :: Software Development :: Libraries :: Python Modules
Requires-Dist: Flask
